{
  "attempt_num": 5,
  "candidate_metadata": {
    "ast_parse_ok": false,
    "parse_error": "no_candidate",
    "redefines_sat": null,
    "sol_arg_count": null
  },
  "created_at": "2026-04-11T08:18:04.409740+00:00",
  "diagnostic": "reason=no_def_sol|parse=fence=python,preamble=1,found_sol=0,candidates=0|preview=The given function `sat` checks if a list has all unique elements. If the length of the list is equal to the length o...",
  "difficulty": "easy",
  "problem_id": "00017_Study_18_0",
  "reward": 0.0,
  "reward_std": 0.0,
  "variant_num": 8
}