{
  "attempt_num": 4,
  "candidate_metadata": {
    "ast_parse_ok": false,
    "parse_error": "invalid syntax",
    "redefines_sat": null,
    "sol_arg_count": null
  },
  "created_at": "2026-04-11T19:09:11.526009+00:00",
  "diagnostic": "reason=ast_syntax_error:invalid syntax|parse=fence=none,preamble=0,found_sol=1,candidates=20|checked=20/20|preview=def sol(): return [8, 284, 72] assert sat([]) assert not sat([[0, 0]]) assert not sat([[0, 1]]) assert not sat([[0, 2...",
  "difficulty": "easy",
  "problem_id": "00090_WaterPouring_2",
  "reward": 0.0,
  "reward_std": 0.0,
  "variant_num": 2
}